phoneshift-0.8.5.dist-info/RECORD
phoneshift-0.8.5.dist-info/WHEEL
phoneshift-0.8.5.dist-info/top_level.txt
phoneshift-0.8.5.dist-info/METADATA
phoneshift-0.8.5.dist-info/licenses/LICENSE.md
phoneshift/__init__.py
phoneshift/sdk_python3_module.cpython-39-darwin.so
phoneshift/tests/license_test.py
phoneshift/tests/__init__.py
phoneshift/tests/nolicense_test.py
phoneshift/tests/utils.py
phoneshift/tests/test_data/wav/female2_assertive_4b_1.wav
phoneshift/doc/LICENSE.md
phoneshift/doc/transformation.html
phoneshift/doc/index.html
phoneshift/doc/license.html
phoneshift/doc/support.html
phoneshift/doc/searchindex.js
phoneshift/doc/genindex.html
phoneshift/doc/attributions.html
phoneshift/doc/misc.html
phoneshift/doc/search.html
phoneshift/doc/installation.html
phoneshift/doc/objects.inv
phoneshift/doc/_sources/support.rst.txt
phoneshift/doc/_sources/attributions.rst.txt
phoneshift/doc/_sources/installation.rst.txt
phoneshift/doc/_sources/transformation.rst.txt
phoneshift/doc/_sources/misc.rst.txt
phoneshift/doc/_sources/index.rst.txt
phoneshift/doc/_sources/license.rst.txt
phoneshift/doc/_static/plus.png
phoneshift/doc/_static/sphinx_highlight.js
phoneshift/doc/_static/icon.png
phoneshift/doc/_static/favicon.ico
phoneshift/doc/_static/documentation_options.js
phoneshift/doc/_static/searchtools.js
phoneshift/doc/_static/debug.css
phoneshift/doc/_static/check-solid.svg
phoneshift/doc/_static/clipboard.min.js
phoneshift/doc/_static/file.png
phoneshift/doc/_static/copybutton.js
phoneshift/doc/_static/language_data.js
phoneshift/doc/_static/copy-button.svg
phoneshift/doc/_static/copybutton_funcs.js
phoneshift/doc/_static/minus.png
phoneshift/doc/_static/skeleton.css
phoneshift/doc/_static/basic.css
phoneshift/doc/_static/pygments.css
phoneshift/doc/_static/copybutton.css
phoneshift/doc/_static/doctools.js
phoneshift/doc/_static/styles/furo.css.map
phoneshift/doc/_static/styles/furo-extensions.css
phoneshift/doc/_static/styles/furo.css
phoneshift/doc/_static/styles/furo-extensions.css.map
phoneshift/doc/_static/scripts/furo.js.LICENSE.txt
phoneshift/doc/_static/scripts/furo.js.map
