Metadata-Version: 2.4
Name: phoneshift
Version: 0.8.5
Summary: Please see https://phoneshift.ing
Home-page: https://phoneshift.ing
Author: Phoneshift
Author-email: dev@phoneshift.ing
License: LicenseRef-Proprietary
Classifier: Programming Language :: Python :: 3
Classifier: Operating System :: OS Independent
Classifier: Development Status :: 1 - Planning
Classifier: Environment :: Console
Requires-Python: >=3.9
License-File: LICENSE.md
Requires-Dist: numpy>=1.0
Dynamic: author
Dynamic: author-email
Dynamic: classifier
Dynamic: description
Dynamic: description-content-type
Dynamic: home-page
Dynamic: license
Dynamic: license-file
Dynamic: requires-dist
Dynamic: requires-python
Dynamic: summary
